MANIFEST.in
README.txt
setup.cfg
setup.py
docs/HISTORY.txt
docs/INSTALL.txt
docs/LICENSE.GPL
docs/LICENSE.txt
plonetheme/__init__.py
plonetheme.delicious2.egg-info/PKG-INFO
plonetheme.delicious2.egg-info/SOURCES.txt
plonetheme.delicious2.egg-info/dependency_links.txt
plonetheme.delicious2.egg-info/entry_points.txt
plonetheme.delicious2.egg-info/namespace_packages.txt
plonetheme.delicious2.egg-info/not-zip-safe
plonetheme.delicious2.egg-info/paster_plugins.txt
plonetheme.delicious2.egg-info/requires.txt
plonetheme.delicious2.egg-info/top_level.txt
plonetheme/delicious2/__init__.py
plonetheme/delicious2/configure.zcml
plonetheme/delicious2/profiles.zcml
plonetheme/delicious2/setuphandlers.py
plonetheme/delicious2/skins.zcml
plonetheme/delicious2/tests.py
plonetheme/delicious2/version.txt
plonetheme/delicious2/browser/__init__.py
plonetheme/delicious2/browser/configure.zcml
plonetheme/delicious2/browser/delicious2_copyright.pt
plonetheme/delicious2/browser/interfaces.py
plonetheme/delicious2/browser/site_actions.pt
plonetheme/delicious2/browser/viewlet.pt
plonetheme/delicious2/browser/viewlets.py
plonetheme/delicious2/browser/images/README.txt
plonetheme/delicious2/browser/images/accessibility.gif
plonetheme/delicious2/browser/images/bg.gif
plonetheme/delicious2/browser/images/button-green.gif
plonetheme/delicious2/browser/images/button.gif
plonetheme/delicious2/browser/images/content-bg.gif
plonetheme/delicious2/browser/images/envelope.gif
plonetheme/delicious2/browser/images/foto.jpg
plonetheme/delicious2/browser/images/h1-bg.gif
plonetheme/delicious2/browser/images/h3-bg.gif
plonetheme/delicious2/browser/images/house.gif
plonetheme/delicious2/browser/images/input-bg.gif
plonetheme/delicious2/browser/images/li-bg-hover.gif
plonetheme/delicious2/browser/images/li-bg.gif
plonetheme/delicious2/browser/images/listing-bg.gif
plonetheme/delicious2/browser/images/portletsVisualWrapper-bg.gif
plonetheme/delicious2/browser/images/printer.gif
plonetheme/delicious2/browser/images/rss.gif
plonetheme/delicious2/browser/images/search-button-big.gif
plonetheme/delicious2/browser/images/search-button.gif
plonetheme/delicious2/browser/images/search-button_mid.gif
plonetheme/delicious2/browser/images/sitemap.gif
plonetheme/delicious2/browser/stylesheets/README.txt
plonetheme/delicious2/browser/stylesheets/main.css
plonetheme/delicious2/profiles/default/cssregistry.xml
